{
  "header": {
    "brand": {
      "border": {
        "color": {
          "value": "{color.grayscale.100.value}",
          "type": "border"
        },
        "width": {
          "value": "{border.width.sm.value}",
          "type": "borderWidth"
        }
      },
      "grid": {
        "gap": {
          "value": "{spacing.100.value}",
          "type": "spacing"
        }
      },
      "padding": {
        "value": "{spacing.100.value} 0 {spacing.200.value}",
        "type": "spacing"
      },
      "toggle": {
        "padding": {
          "value": "0 {spacing.225.value}",
          "type": "spacing"
        }
      }
    },
    "container": {
      "maxWidth": {
        "value": "{container.xl.value}",
        "type": "sizing"
      }
    },
    "margin": {
      "value": "0 0 {spacing.750.value}",
      "type": "spacing"
    },
    "skiptonav": {
      "top": {
        "value": "{spacing.150.value}",
        "type": "spacing"
      }
    }
  }
}
