{
  "color": {
    "blue": {
      "focus": {
        "value": "#303FC3",
        "type": "color"
      },
      "100": {
        "value": "#D7E5F5",
        "type": "color"
      },
      "700": {
        "value": "#425A76",
        "type": "color"
      },
      "800": {
        "value": "#31455C",
        "type": "color"
      },
      "900": {
        "value": "#26374A",
        "type": "color"
      }
    },
    "grayscale": {
      "0": {
        "value": "#FFF",
        "type": "color"
      },
      "100": {
        "value": "#F0F0F0",
        "type": "color"
      },
      "300": {
        "value": "#E0E2E5",
        "type": "color"
      },
      "500": {
        "value": "#B6BABF",
        "type": "color"
      },
      "700": {
        "value": "#747A82",
        "type": "color"
      },
      "900": {
        "value": "#545961",
        "type": "color"
      },
      "1000": {
        "value": "#000",
        "type": "color"
      }
    },
    "green": {
      "100": {
        "value": "#ECF3EC",
        "type": "color"
      },
      "200": {
        "value": "#005900",
        "type": "color"
      }
    },
    "red": {
      "flag": {
        "value": "#FF0000",
        "type": "color"
      },
      "100": {
        "value": "#FBDDDA",
        "type": "color"
      },
      "700": {
        "value": "#A62A1E",
        "type": "color"
      },
      "900": {
        "value": "#822117",
        "type": "color"
      }
    },
    "yellow": {
      "100": {
        "value": "#FAF3D1",
        "type": "color"
      },
      "200": {
        "value": "#f7b452",
        "type": "color"
      }
    }
  }
}
